pkg_lld
