Metadata-Version: 2.1
Name: ey-genai-pkgs
Version: 0.2
Summary: Generate boiler plate code from LLD docx
Author: Rohan
